odoo/addons/stock_location_address/README.rst
odoo/addons/stock_location_address/__init__.py
odoo/addons/stock_location_address/__manifest__.py
odoo/addons/stock_location_address/i18n/it.po
odoo/addons/stock_location_address/i18n/stock_location_address.pot
odoo/addons/stock_location_address/models/__init__.py
odoo/addons/stock_location_address/models/stock_location.py
odoo/addons/stock_location_address/readme/CONTRIBUTORS.rst
odoo/addons/stock_location_address/readme/DESCRIPTION.rst
odoo/addons/stock_location_address/readme/USAGE.rst
odoo/addons/stock_location_address/static/description/icon.png
odoo/addons/stock_location_address/static/description/index.html
odoo/addons/stock_location_address/tests/__init__.py
odoo/addons/stock_location_address/tests/test_location_address.py
odoo/addons/stock_location_address/views/stock_location_views.xml
odoo14_addon_stock_location_address-14.0.1.0.1.dev6.dist-info/METADATA
odoo14_addon_stock_location_address-14.0.1.0.1.dev6.dist-info/WHEEL
odoo14_addon_stock_location_address-14.0.1.0.1.dev6.dist-info/top_level.txt
odoo14_addon_stock_location_address-14.0.1.0.1.dev6.dist-info/RECORD
